skreader/__init__.py
skreader/cli.py
skreader/const.py
skreader/controller.py
skreader/conv.py
skreader/device.py
skreader/measurement.py
skreader/testdata.py
skreader/usbadapter.py
skreader-1.0.0.dist-info/LICENSE.md
skreader-1.0.0.dist-info/METADATA
skreader-1.0.0.dist-info/WHEEL
skreader-1.0.0.dist-info/entry_points.txt
skreader-1.0.0.dist-info/RECORD
