Metadata-Version: 2.3
Name: skreader
Version: 1.0.0
Summary: Python library and command line tool for SEKONIC spectrometers remote control.
License: MIT
Author: Oleksandr Reshetniak
Requires-Python: >=3.9
Classifier: Intended Audience :: Developers
Classifier: License :: OSI Approved :: MIT License
Classifier: Operating System :: MacOS :: MacOS X
Classifier: Operating System :: Microsoft :: Windows
Classifier: Operating System :: POSIX :: Linux
Classifier: Programming Language :: Python :: 3
Classifier: Programming Language :: Python :: 3.9
Classifier: Programming Language :: Python :: 3.10
Classifier: Programming Language :: Python :: 3.11
Classifier: Programming Language :: Python :: 3.12
Classifier: Programming Language :: Python :: 3.13
Classifier: Topic :: Software Development :: Libraries :: Python Modules
Classifier: Topic :: System :: Hardware :: Universal Serial Bus (USB)
Requires-Dist: pyusb (>=1.2.1)
Requires-Dist: rich-argparse (>=1.7.0,<2.0.0)
Project-URL: Homepage, https://github.com/akares/skreader-py
Project-URL: Repository, https://github.com/akares/skreader-py
